fluxy/__init__.py
fluxy/fluxy_fastapi.py
fluxy/validate.py
fluxy-0.3.15.dist-info/METADATA
fluxy-0.3.15.dist-info/WHEEL
fluxy-0.3.15.dist-info/entry_points.txt
fluxy-0.3.15.dist-info/top_level.txt
fluxy-0.3.15.dist-info/RECORD
