Metadata-Version: 2.1
Name: fluxy
Version: 0.3.15
Requires-Dist: click
Requires-Dist: fastapi
Requires-Dist: uvicorn
